{
  "placeholderImages": [
    {
      "id": "blog-post-1",
      "description": "Abstract image representing sustainable growth and customer retention.",
      "imageUrl": "https://picsum.photos/seed/blog1/600/400",
      "imageHint": "growth abstract"
    },
    {
      "id": "blog-post-crm-1",
      "description": "An image for the introduction section of the Customer Retention Management blog post.",
      "imageUrl": "/images/ritnge.webp",
      "imageHint": "business strategy"
    },
    {
      "id": "blog-post-crm-2",
      "description": "An image for the technology section of the Customer Retention Management blog post.",
      "imageUrl": "/images/crs.webp",
      "imageHint": "technology system"
    },
    {
      "id": "blog-post-crm-3",
      "description": "An image for the examples section of the Customer Retention Management blog post.",
      "imageUrl": "/images/cre.webp",
      "imageHint": "customer success"
    },
    {
      "id": "sample-post-1",
      "description": "A placeholder image for the sample blog post.",
      "imageUrl": "/images/sample-post.jpg",
      "imageHint": "abstract placeholder"
    }
  ]
}